Workbook

Sheet Tổng quan
A1: ĐẶC TẢ YÊU CẦU — HỆ THỐNG BÁN HÀNG TÍCH HỢP AI
A2: Đồ án thực tập Fullstack: Vue.js 3 + TypeScript / Django (Python 3.12) / PostgreSQL / Docker — tích hợp AI
A4: 1. MỤC TIÊU
A5: Xây dựng sàn thương mại điện tử đa gian hàng (multi-vendor) gồm 3 vai trò: Admin hệ thống, Nhà bán hàng (Seller) và Khách hàng (Customer). Hệ thống hỗ trợ đầy đủ nghiệp vụ bán hàng (sản phẩm, kho, giỏ hàng, đặt hàng, khuyến mãi, đánh giá, chat) và tích hợp AI để nâng cao trải nghiệm tìm kiếm, mua sắm và quản trị.
A7: 2. VAI TRÒ NGƯỜI DÙNG
A8: Vai trò | B8: Mô tả | C8: Sheet chi tiết
A9: Admin hệ thống | B9: Quản trị toàn sàn: người dùng, seller, sản phẩm, đơn hàng, khuyến mãi, báo cáo. | C9: Admin
A10: Nhà bán hàng (Seller) | B10: Quản lý gian hàng: sản phẩm, kho, đơn hàng, voucher shop, chat với khách. | C10: Seller
A11: Khách hàng (Customer) | B11: Mua sắm: tìm kiếm, giỏ hàng, đặt hàng, thanh toán, đánh giá, chat với shop. | C11: Customer
A13: 3. THỐNG KÊ YÊU CẦU & TIẾN ĐỘ
A14: Nhóm yêu cầu | B14: Tổng số | C14: Bắt buộc | D14: Nên có | E14: Tùy chọn | F14: Hoàn thành | G14: % hoàn thành
A15: Admin | B15: =COUNTA(Admin!$A$3:$A$28) -> 26 | C15: =COUNTIF(Admin!$E$3:$E$28,"Bắt buộc") -> 16 | D15: =COUNTIF(Admin!$E$3:$E$28,"Nên có") -> 8 | E15: =COUNTIF(Admin!$E$3:$E$28,"Tùy chọn") -> 2 | F15: =COUNTIF(Admin!$H$3:$H$28,"Hoàn thành") -> 0 | G15: =IF(B15=0,0,F15/B15) -> 0
A16: Seller | B16: =COUNTA(Seller!$A$3:$A$20) -> 18 | C16: =COUNTIF(Seller!$E$3:$E$20,"Bắt buộc") -> 14 | D16: =COUNTIF(Seller!$E$3:$E$20,"Nên có") -> 4 | E16: =COUNTIF(Seller!$E$3:$E$20,"Tùy chọn") -> 0 | F16: =COUNTIF(Seller!$H$3:$H$20,"Hoàn thành") -> 0 | G16: =IF(B16=0,0,F16/B16) -> 0
A17: Customer | B17: =COUNTA(Customer!$A$3:$A$24) -> 22 | C17: =COUNTIF(Customer!$E$3:$E$24,"Bắt buộc") -> 19 | D17: =COUNTIF(Customer!$E$3:$E$24,"Nên có") -> 2 | E17: =COUNTIF(Customer!$E$3:$E$24,"Tùy chọn") -> 1 | F17: =COUNTIF(Customer!$H$3:$H$24,"Hoàn thành") -> 0 | G17: =IF(B17=0,0,F17/B17) -> 0
A18: Tính năng AI | B18: =COUNTA(AI!$A$3:$A$17) -> 15 | C18: =COUNTIF(AI!$E$3:$E$17,"Bắt buộc") -> 5 | D18: =COUNTIF(AI!$E$3:$E$17,"Nên có") -> 3 | E18: =COUNTIF(AI!$E$3:$E$17,"Tùy chọn") -> 7 | F18: =COUNTIF(AI!$H$3:$H$17,"Hoàn thành") -> 0 | G18: =IF(B18=0,0,F18/B18) -> 0
A19: Bonus | B19: =COUNTA(Bonus!$A$3:$A$16) -> 14 | C19: =COUNTIF(Bonus!$E$3:$E$16,"Bắt buộc") -> 0 | D19: =COUNTIF(Bonus!$E$3:$E$16,"Nên có") -> 2 | E19: =COUNTIF(Bonus!$E$3:$E$16,"Tùy chọn") -> 12 | F19: =COUNTIF(Bonus!$H$3:$H$16,"Hoàn thành") -> 0 | G19: =IF(B19=0,0,F19/B19) -> 0
A20: Phi chức năng | B20: =COUNTA('Phi chức năng'!$A$3:$A$18) -> 16 | C20: =COUNTIF('Phi chức năng'!$E$3:$E$18,"Bắt buộc") -> 11 | D20: =COUNTIF('Phi chức năng'!$E$3:$E$18,"Nên có") -> 4 | E20: =COUNTIF('Phi chức năng'!$E$3:$E$18,"Tùy chọn") -> 1 | F20: =COUNTIF('Phi chức năng'!$H$3:$H$18,"Hoàn thành") -> 0 | G20: =IF(B20=0,0,F20/B20) -> 0
A21: TỔNG | B21: =SUM(B15:B20) -> 111 | C21: =SUM(C15:C20) -> 65 | D21: =SUM(D15:D20) -> 23 | E21: =SUM(E15:E20) -> 23 | F21: =SUM(F15:F20) -> 0 | G21: =IF(B21=0,0,F21/B21) -> 0
A23: 4. SẢN PHẨM BÀN GIAO
A24: 1. Source code Frontend (Vue 3 + TypeScript) và Backend (Django) trên Git repository, có README hướng dẫn chạy.
A25: 2. docker-compose.yml chạy được toàn bộ hệ thống bằng 1 lệnh (FE, BE, Celery, Redis, Nginx; PostgreSQL external qua env).
A26: 3. Tài liệu API (Swagger/OpenAPI) và sơ đồ ERD cơ sở dữ liệu.
A27: 4. File .env.example liệt kê đầy đủ biến môi trường (DB, JWT secret, AI API key, payment sandbox...).
A28: 5. Seed data mẫu (danh mục, sản phẩm, tài khoản 3 vai trò) để demo được ngay.
A29: 6. Bản demo + slide trình bày: kiến trúc hệ thống, luồng nghiệp vụ chính, các tính năng AI đã làm.
A31: 5. HƯỚNG DẪN DÙNG FILE NÀY
A32: • Mỗi sheet là một nhóm yêu cầu; cột 'Độ ưu tiên': Bắt buộc = phải hoàn thành, Nên có = làm khi đã xong phần bắt buộc, Tùy chọn = điểm cộng.
A33: • Cột 'Trạng thái' (Chưa làm / Đang làm / Hoàn thành) do người thực hiện cập nhật — bảng mục 3 ở trên tự tính % tiến độ.
A34: • Cột 'Gợi ý kỹ thuật' chỉ là định hướng, người thực hiện được phép chọn giải pháp khác nếu giải thích được lý do.
A35: • Sheet 'Đánh giá' là thang điểm tham chiếu khi chấm đồ án.

Sheet Công nghệ
A1: YÊU CẦU CÔNG NGHỆ & MÔI TRƯỜNG
A2: Nhóm | B2: Công nghệ / Hạng mục | C2: Phiên bản / Yêu cầu | D2: Ghi chú
A3: Frontend | B3: Node.js | C3: 20 LTS | D3: Môi trường build & dev server.
A4: Frontend | B4: Vue.js | C4: 3.x — Composition API + <script setup> | D4: Framework SPA chính.
A5: Frontend | B5: TypeScript | C5: 5.x, strict mode | D5: Bắt buộc toàn bộ code FE có type.
A6: Frontend | B6: Vite | C6: 5.x | D6: Build tool & dev server.
A7: Frontend | B7: Pinia | C7: 2.x | D7: State management (auth, cart, notification...).
A8: Frontend | B8: Vue Router | C8: 4.x | D8: Routing + route guard theo vai trò.
A9: Frontend | B9: CSS Framework | C9: Tailwind CSS (khuyến nghị) hoặc Bootstrap 5 | D9: Chọn 1, dùng nhất quán toàn dự án.
A10: Frontend | B10: Icon | C10: Heroicons hoặc FontAwesome | D10: Chọn 1 bộ icon thống nhất.
A11: Frontend | B11: HTTP Client | C11: Axios | D11: Instance chung + interceptor refresh token.
A12: Frontend | B12: Biểu đồ | C12: Chart.js / ApexCharts | D12: Dashboard Admin & Seller.
A13: Backend | B13: Python | C13: 3.12 | D13: Phiên bản cố định trong Dockerfile.
... A28: Khác | B28: Git | C28: Git flow đơn giản (main / develop / feature) | D28: Commit message rõ ràng; PR tự review.

Sheet Admin
A1: YÊU CẦU CHỨC NĂNG — ADMIN HỆ THỐNG
A2: Mã YC | B2: Module | C2: Chức năng | D2: Mô tả chi tiết | E2: Độ ưu tiên | F2: Độ khó | G2: Gợi ý kỹ thuật | H2: Trạng thái
A3: ADM-01 | B3: Dashboard | C3: Thẻ thống kê tổng quan | D3: Hiển thị các thẻ số liệu: tổng doanh thu toàn sàn, tổng số đơn hàng, tổng người dùng, tổng nhà bán hàng đang hoạt động. Số liệu cập nhật theo bộ lọc thời gian (hôm nay / 7 ngày / 30 ngày / tùy chọn). | E3: Bắt buộc | F3: Trung bình | G3: Django ORM aggregate (Sum, Count); API riêng cho dashboard; cache Redis 5 phút để giảm tải. | H3: Chưa làm
A4: ADM-02 | B4: Dashboard | C4: Biểu đồ doanh thu | D4: Biểu đồ đường/cột doanh thu theo ngày/tuần/tháng, cho phép chọn khoảng thời gian. So sánh với kỳ trước (tăng/giảm %). | E4: Bắt buộc | F4: Trung bình | G4: Chart.js hoặc ApexCharts trên Vue; API trả về series đã group theo TruncDate/TruncMonth. | H4: Chưa làm
A5: ADM-03 | B5: Dashboard | C5: Top sản phẩm bán chạy | D5: Danh sách 10 sản phẩm có số lượng bán cao nhất kèm doanh thu, hình ảnh, seller sở hữu. Lọc theo khoảng thời gian. | E5: Bắt buộc | F5: Dễ | G5: Annotate Sum(quantity) trên OrderItem, order_by giảm dần, limit 10. | H5: Chưa làm
A6: ADM-04 | B6: Quản lý người dùng | C6: CRUD khách hàng | D6: Xem danh sách khách hàng (phân trang, tìm kiếm theo tên/email/SĐT), xem chi tiết, tạo mới, cập nhật thông tin, xóa mềm (soft delete). | E6: Bắt buộc | F6: Dễ | G6: DRF ModelViewSet + SearchFilter; soft delete bằng cờ is_deleted; phân trang PageNumberPagination. | H6: Chưa làm
A7: ADM-05 | B7: Quản lý người dùng | C7: CRUD nhà bán hàng | D7: Quản lý danh sách seller: xem, sửa thông tin gian hàng, xóa mềm. Hiển thị trạng thái duyệt (chờ duyệt / đã duyệt / bị khóa). | E7: Bắt buộc | F7: Dễ | G7: Model SellerProfile quan hệ 1-1 với User; filter theo trạng thái. | H7: Chưa làm
A8: ADM-06 | B8: Quản lý người dùng | C8: Khóa / mở khóa tài khoản | D8: Admin khóa tài khoản vi phạm (user không đăng nhập được, seller không bán được), mở khóa kèm lý do. Gửi email thông báo cho người bị khóa. | E8: Bắt buộc | F8: Dễ | G8: Cờ is_active của Django User; middleware/permission chặn token của user bị khóa; gửi mail bằng Celery. | H8: Chưa làm
A9: ADM-07 | B9: Quản lý người dùng | C9: Reset mật khẩu người dùng | D9: Admin chủ động reset mật khẩu cho người dùng: sinh mật khẩu tạm hoặc gửi link đặt lại qua email, bắt buộc đổi mật khẩu ở lần đăng nhập kế tiếp. | E9: Bắt buộc | F9: Dễ | G9: Django PasswordResetTokenGenerator; email template; cờ must_change_password. | H9: Chưa làm
A10: ADM-08 | B10: Quản lý người dùng | C10: Phân quyền (RBAC) | D10: Hệ thống 3 vai trò: Admin, Seller, Customer. Mỗi API chỉ cho phép vai trò phù hợp truy cập. Admin có thể gán/thu hồi vai trò. | E10: Bắt buộc | F10: Trung bình | G10: DRF custom Permission class; JWT chứa role claim; route guard trên Vue Router theo role. | H10: Chưa làm
A11: ADM-09 | B11: Quản lý seller | C11: Duyệt đăng ký seller | D11: Danh sách hồ sơ đăng ký bán hàng chờ duyệt; Admin xem chi tiết, duyệt hoặc từ chối kèm lý do. Kết quả gửi thông báo/email cho người đăng ký. | E11: Bắt buộc | F11: Trung bình | G11: Trạng thái hồ sơ: pending → approved/rejected; signal gửi notification khi đổi trạng thái. | H11: Chưa làm
A12: ADM-10 | B12: Quản lý seller | C12: Xác minh thông tin gian hàng | D12: Xem giấy tờ/thông tin xác minh do seller upload (CCCD, giấy phép KD...). Đánh dấu đã xác minh, yêu cầu bổ sung nếu thiếu. | E12: Nên có | F12: Trung bình | G12: Upload file lên storage (local/S3-compatible); trạng thái xác minh riêng từng loại giấy tờ. | H12: Chưa làm
A13: ADM-11 | B13: Quản lý seller | C13: Khóa gian hàng | D13: Khóa toàn bộ gian hàng vi phạm: sản phẩm bị ẩn khỏi trang mua sắm, seller không tạo đơn/sản phẩm mới nhưng vẫn xử lý đơn cũ. | E13: Bắt buộc | F13: Trung bình | G13: Cờ shop_status; queryset sản phẩm public luôn filter theo trạng thái shop. | H13: Chưa làm
... A28: ADM-26 | B28: Hệ thống | C28: Cấu hình hệ thống | D28: Trang cấu hình tham số chung: phí sàn (%), ngưỡng cảnh báo tồn kho mặc định, email liên hệ, bật/tắt tính năng (feature flag). | E28: Tùy chọn | F28: Dễ | G28: Bảng SiteSetting dạng key-value; cache lại; API get/put cho Admin. | H28: Chưa làm

Sheet Seller
A1: YÊU CẦU CHỨC NĂNG — NHÀ BÁN HÀNG (SELLER)
A2: Mã YC | B2: Module | C2: Chức năng | D2: Mô tả chi tiết | E2: Độ ưu tiên | F2: Độ khó | G2: Gợi ý kỹ thuật | H2: Trạng thái
A3: SEL-01 | B3: Dashboard | C3: Thống kê gian hàng | D3: Thẻ số liệu của shop: doanh thu (hôm nay/tháng), đơn mới chờ xử lý, đơn hoàn thành, đơn hủy, số sản phẩm sắp hết hàng. Biểu đồ doanh thu 30 ngày. | E3: Bắt buộc | F3: Trung bình | G3: API dashboard riêng scope theo seller đăng nhập; tái sử dụng component biểu đồ với Admin. | H3: Chưa làm
A4: SEL-02 | B4: Quản lý sản phẩm | C4: CRUD sản phẩm | D4: Tạo/sửa/xóa mềm sản phẩm: tên, danh mục, thương hiệu, giá gốc, giá bán, mô tả rich-text, trạng thái (nháp/đang bán/ngừng bán). Danh sách có tìm kiếm, lọc theo trạng thái/danh mục. | E4: Bắt buộc | F4: Trung bình | G4: DRF nested serializer; editor rich-text (TipTap/Quill) trên Vue; slug tự sinh, unique theo shop. | H4: Chưa làm
A5: SEL-03 | B5: Quản lý sản phẩm | C5: Upload nhiều ảnh & video | D5: Mỗi sản phẩm tối đa 9 ảnh + 1 video; kéo thả sắp xếp thứ tự, chọn ảnh đại diện; validate dung lượng/định dạng; ảnh được nén và sinh thumbnail. | E5: Bắt buộc | F5: Trung bình | G5: Model ProductMedia; Pillow resize + thumbnail; upload multipart hoặc presigned URL; vuedraggable sắp xếp. | H5: Chưa làm
A6: SEL-04 | B6: Quản lý sản phẩm | C6: Biến thể sản phẩm (size, màu...) | D6: Định nghĩa thuộc tính (màu, size...) và tổ hợp biến thể; mỗi biến thể có SKU riêng, barcode, giá riêng, tồn kho riêng, ảnh riêng. Sinh tổ hợp tự động từ các thuộc tính. | E6: Bắt buộc | F6: Khó | G6: Model Attribute/AttributeValue/ProductVariant; unique SKU; UI ma trận biến thể trên Vue. | H6: Chưa làm
A7: SEL-05 | B7: Quản lý sản phẩm | C7: SKU & Barcode | D7: Mỗi biến thể có SKU (tự sinh theo quy tắc hoặc nhập tay) và barcode. In tem barcode; quét barcode khi nhập/xuất kho là điểm cộng. | E7: Nên có | F7: Trung bình | G7: python-barcode/qrcode sinh ảnh; validate trùng SKU trong shop. | H7: Chưa làm
A8: SEL-06 | B8: Quản lý kho | C8: Nhập kho | D8: Tạo phiếu nhập: chọn sản phẩm/biến thể, số lượng, giá nhập, nhà cung cấp, ghi chú. Xác nhận phiếu thì cộng tồn kho. | E8: Bắt buộc | F8: Trung bình | G8: Model StockEntry + StockEntryItem; transaction.atomic khi cập nhật tồn; không sửa phiếu đã xác nhận. | H8: Chưa làm
A9: SEL-07 | B9: Quản lý kho | C9: Xuất kho & điều chỉnh tồn | D9: Phiếu xuất (hủy hàng, trả NCC) và phiếu kiểm kê điều chỉnh tồn thực tế, bắt buộc nhập lý do. Tồn kho không được âm. | E9: Bắt buộc | F9: Trung bình | G9: CheckConstraint stock >= 0; select_for_update tránh race khi trừ tồn. | H9: Chưa làm
A10: SEL-08 | B10: Quản lý kho | C10: Lịch sử nhập / xuất | D10: Sổ kho từng biến thể: mọi biến động tồn (nhập, xuất, bán, hoàn, điều chỉnh) kèm thời gian, người thao tác, số dư sau giao dịch. | E10: Bắt buộc | F10: Dễ | G10: Bảng StockMovement append-only; mọi thay đổi tồn đều đi qua một service duy nhất. | H10: Chưa làm
A11: SEL-09 | B11: Quản lý kho | C11: Cảnh báo sắp hết hàng | D11: Seller đặt ngưỡng tồn tối thiểu từng sản phẩm; hệ thống hiển thị danh sách sắp hết và gửi thông báo khi chạm ngưỡng. | E11: Bắt buộc | F11: Dễ | G11: Trường low_stock_threshold; Celery beat quét hằng ngày hoặc check ngay khi trừ tồn; notification in-app. | H11: Chưa làm
A12: SEL-10 | B12: Quản lý đơn hàng | C12: Luồng xử lý đơn | D12: Xử lý đơn theo luồng: Chờ xác nhận → Đã xác nhận → Đang đóng gói → Đang giao → Hoàn thành; hoặc Hủy (kèm lý do, hoàn tồn kho). Mỗi bước ghi lịch sử và bắn thông báo cho khách. | E12: Bắt buộc | F12: Trung bình | G12: State machine kiểm soát bước chuyển hợp lệ; OrderStatusHistory; hoàn tồn khi hủy trong transaction. | H12: Chưa làm
A13: SEL-11 | B13: Quản lý đơn hàng | C13: In phiếu giao / đóng gói | D13: In phiếu giao hàng (địa chỉ, mã đơn, QR/mã vạch, danh sách hàng) phục vụ đóng gói. | E13: Nên có | F13: Dễ | G13: Template HTML in ấn hoặc PDF (WeasyPrint); QR chứa mã đơn. | H13: Chưa làm
... A20: SEL-18 | B20: Hồ sơ shop | C20: Đăng ký bán hàng | D20: Customer đăng ký trở thành seller: điền thông tin shop, upload giấy tờ, gửi duyệt; theo dõi trạng thái hồ sơ. | E20: Bắt buộc | F20: Trung bình | G20: Form nhiều bước trên Vue; hồ sơ pending chờ Admin duyệt (khớp ADM-09). | H20: Chưa làm

Sheet Customer
A1: YÊU CẦU CHỨC NĂNG — KHÁCH HÀNG (CUSTOMER)
A2: Mã YC | B2: Module | C2: Chức năng | D2: Mô tả chi tiết | E2: Độ ưu tiên | F2: Độ khó | G2: Gợi ý kỹ thuật | H2: Trạng thái
A3: CUS-01 | B3: Tài khoản | C3: Đăng ký | D3: Đăng ký bằng email + mật khẩu: validate email hợp lệ, mật khẩu đủ mạnh; gửi email xác thực kích hoạt tài khoản. | E3: Bắt buộc | F3: Dễ | G3: DRF endpoint register; mật khẩu hash chuẩn Django; email verify token có hạn. | H3: Chưa làm
A4: CUS-02 | B4: Tài khoản | C4: Đăng nhập / đăng xuất | D4: Đăng nhập email + mật khẩu, trả JWT (access + refresh); tự refresh token khi hết hạn; đăng xuất thu hồi refresh token; khóa tạm sau nhiều lần sai (rate limit). | E4: Bắt buộc | F4: Trung bình | G4: djangorestframework-simplejwt; axios interceptor refresh; blacklist refresh token; django-ratelimit. | H4: Chưa làm
A5: CUS-03 | B5: Tài khoản | C5: Google Login | D5: Đăng nhập nhanh bằng tài khoản Google (OAuth2); tự tạo tài khoản lần đầu và liên kết với tài khoản email trùng nếu có. | E5: Tùy chọn | F5: Trung bình | G5: Google Identity Services trên FE lấy id_token; BE verify token, get_or_create user. | H5: Chưa làm
A6: CUS-04 | B6: Tài khoản | C6: Quên mật khẩu | D6: Gửi link đặt lại mật khẩu qua email, link có thời hạn; đặt mật khẩu mới và vô hiệu link cũ. | E6: Bắt buộc | F6: Dễ | G6: PasswordResetTokenGenerator; trang reset trên Vue nhận token qua query. | H6: Chưa làm
A7: CUS-05 | B7: Tài khoản | C7: Hồ sơ cá nhân | D7: Xem/sửa thông tin: họ tên, ảnh đại diện, SĐT, ngày sinh, giới tính; đổi mật khẩu (yêu cầu mật khẩu cũ). | E7: Bắt buộc | F7: Dễ | G7: Endpoint /me; upload avatar có crop phía FE. | H7: Chưa làm
A8: CUS-06 | B8: Tài khoản | C8: Sổ địa chỉ | D8: CRUD nhiều địa chỉ nhận hàng: người nhận, SĐT, tỉnh/huyện/xã (dropdown 3 cấp), địa chỉ chi tiết, đặt mặc định. | E8: Bắt buộc | F8: Trung bình | G8: Dữ liệu đơn vị hành chính VN (seed sẵn); mỗi user 1 địa chỉ mặc định (partial unique index). | H8: Chưa làm
A9: CUS-07 | B9: Trang chủ | C9: Banner & khối nội dung | D9: Trang chủ gồm: carousel banner, khối Flash Sale đang chạy (kèm đồng hồ đếm ngược), sản phẩm gợi ý cho bạn, sản phẩm mới, bán chạy, danh mục nổi bật. | E9: Bắt buộc | F9: Trung bình | G9: Một API tổng hợp trả các khối; lazy-load từng khối; skeleton loading trên Vue. | H9: Chưa làm
A10: CUS-08 | B10: Tìm kiếm & Lọc | C10: Tìm kiếm theo từ khóa | D10: Ô tìm kiếm ở header, gợi ý từ khóa/sản phẩm khi gõ (autocomplete, debounce); trang kết quả phân trang. | E10: Bắt buộc | F10: Trung bình | G10: PostgreSQL full-text search hoặc trigram (pg_trgm) cho tiếng Việt; debounce 300ms. | H10: Chưa làm
A11: CUS-09 | B11: Tìm kiếm & Lọc | C11: Bộ lọc & sắp xếp đa tiêu chí | D11: Lọc kết hợp: danh mục, khoảng giá, thương hiệu, đánh giá tối thiểu, màu/size, còn hàng; sắp xếp theo giá, mới nhất, bán chạy, đánh giá. Bộ lọc đồng bộ lên URL để chia sẻ được. | E11: Bắt buộc | F11: Trung bình | G11: django-filter; query params đồng bộ Vue Router; đếm số lượng theo từng facet là điểm cộng. | H11: Chưa làm
A12: CUS-10 | B12: Chi tiết sản phẩm | C12: Trang chi tiết | D12: Gallery ảnh + video (zoom, swipe mobile); chọn biến thể (màu/size) — giá & tồn kho đổi theo; thông số kỹ thuật dạng bảng; mô tả rich-text; sản phẩm cùng shop và tương tự. | E12: Bắt buộc | F12: Trung bình | G12: API detail trả kèm variants + media; component gallery (swiper); cập nhật giá theo variant chọn. | H12: Chưa làm
A13: CUS-11 | B13: Chi tiết sản phẩm | C13: Review & hỏi đáp (Q&A) | D13: Xem đánh giá có lọc theo số sao / có ảnh; khu vực Q&A: khách đặt câu hỏi, seller trả lời, hiển thị công khai. | E13: Bắt buộc | F13: Trung bình | G13: Model Question/Answer; review chỉ từ người đã mua (verified purchase). | H13: Chưa làm
... A24: CUS-22 | B24: Giao diện | C24: Responsive & UX cơ bản | D24: Toàn bộ trang khách hàng responsive mobile-first; skeleton loading; trang 404/500; SEO cơ bản (title, meta) cho trang sản phẩm. | E24: Bắt buộc | F24: Trung bình | G24: Tailwind breakpoints; vue-meta/useHead; kiểm tra Lighthouse. | H24: Chưa làm

Sheet AI
A1: YÊU CẦU TÍNH NĂNG AI
A2: Mã YC | B2: Module | C2: Chức năng | D2: Mô tả chi tiết | E2: Độ ưu tiên | F2: Độ khó | G2: Gợi ý kỹ thuật | H2: Trạng thái
A3: AI-01 | B3: Tìm kiếm | C3: AI Smart Search (tìm theo nhu cầu) | D3: Người dùng nhập nhu cầu tự nhiên (VD: 'laptop học AI dưới 20 triệu', 'quà sinh nhật cho bạn gái'); hệ thống hiểu ý định, trích xuất ràng buộc (loại hàng, giá, thuộc tính) và trả về sản phẩm phù hợp kèm giải thích ngắn vì sao gợi ý. | E3: Tùy chọn | F3: Khó | G3: LLM trích xuất structured filter (function calling) + semantic search bằng embeddings (pgvector); kết hợp lọc SQL theo giá/danh mục. | H3: Chưa làm
A4: AI-02 | B4: Tìm kiếm | C4: Semantic search bằng embeddings | D4: Đánh index toàn bộ sản phẩm thành vector (tên + mô tả + thuộc tính); truy vấn được embed và tìm k sản phẩm gần nhất; kết hợp với keyword search (hybrid). | E4: Tùy chọn | F4: Khó | G4: pgvector trên PostgreSQL (cosine); model embedding đa ngôn ngữ (VD text-embedding-3-small hoặc model tiếng Việt); Celery re-index khi sản phẩm thay đổi. | H4: Chưa làm
A5: AI-03 | B5: Gợi ý | C5: AI Recommendation cá nhân hóa | D5: Khối 'Gợi ý cho bạn' dựa trên lịch sử xem, lịch sử mua và giỏ hàng hiện tại; khách mới thấy sản phẩm phổ biến (cold start). | E5: Tùy chọn | F5: Khó | G5: Bắt đầu bằng content-based trên embeddings từ lịch sử tương tác; ghi log ProductView; nâng cấp collaborative filtering nếu kịp. | H5: Chưa làm
A6: AI-04 | B6: Gợi ý | C6: AI Similar Products | D6: Khối 'Sản phẩm tương tự' ở trang chi tiết dựa trên độ tương đồng nội dung, không chỉ cùng danh mục. | E6: Tùy chọn | F6: Trung bình | G6: k-NN trên vector sản phẩm (pgvector); cache kết quả theo product_id. | H6: Chưa làm
A7: AI-05 | B7: Trợ lý | C7: AI Shopping Assistant (chatbot) | D7: Chatbot hội thoại nhiều lượt tư vấn mua hàng: hỏi lại làm rõ nhu cầu, tìm và đề xuất sản phẩm thật của sàn (kèm card sản phẩm bấm được), so sánh, trả lời về chính sách giao/đổi trả. | E7: Tùy chọn | F7: Khó | G7: LLM + tool use (search_products, get_product, get_policy); giữ ngữ cảnh hội thoại theo session; stream câu trả lời qua SSE/WebSocket. | H7: Chưa làm
A8: AI-06 | B8: Trợ lý | C8: AI Customer Support tự động | D8: Tự động trả lời câu hỏi phổ biến của khách trong chat (phí ship, thời gian giao, đổi trả, trạng thái đơn...); câu khó thì chuyển tiếp cho seller/CSKH kèm tóm tắt. | E8: Nên có | F8: Khó | G8: RAG trên bộ FAQ + chính sách; ngưỡng confidence để quyết định auto-reply hay handoff. | H8: Chưa làm
A9: AI-07 | B9: Nội dung | C9: AI Review Summary | D9: Trang sản phẩm hiển thị tóm tắt AI từ toàn bộ đánh giá: ưu điểm chính, nhược điểm chính, tỷ lệ hài lòng ước tính; tự cập nhật khi có nhiều review mới. | E9: Bắt buộc | F9: Trung bình | G9: LLM summarize theo batch; cache kết quả trong DB, re-generate qua Celery khi đủ N review mới; hiển thị kèm nhãn 'Tạo bởi AI'. | H9: Chưa làm
A10: AI-08 | B10: Nội dung | C10: AI Product Summary | D10: Nút 'Tóm tắt nhanh' rút gọn mô tả dài của sản phẩm thành các gạch đầu dòng dễ đọc. | E10: Bắt buộc | F10: Dễ | G10: Prompt summarize; cache theo product + hash mô tả để không gọi lại thừa. | H10: Chưa làm
A11: AI-09 | B11: Nội dung | C11: AI Compare (so sánh sản phẩm) | D11: Khách chọn 2-4 sản phẩm để so sánh; AI sinh bảng so sánh thông số + nhận xét nên chọn sản phẩm nào theo từng nhu cầu. | E11: Bắt buộc | F11: Trung bình | G11: Gom structured data các sản phẩm đưa vào prompt; yêu cầu LLM trả JSON để render bảng trên Vue. | H11: Chưa làm
A12: AI-10 | B12: Hỗ trợ seller | C12: AI Generate Description | D12: Trong form tạo sản phẩm, seller nhập tên + vài từ khóa; AI sinh tiêu đề chuẩn SEO, mô tả bán hàng hấp dẫn, meta description; seller sửa lại trước khi lưu. | E12: Bắt buộc | F12: Trung bình | G12: Prompt template có tone thương mại; trả về structured (title/description/seo); nút regenerate. | H12: Chưa làm
A13: AI-11 | B13: Hỗ trợ seller | C13: AI Auto Tag & phân loại | D13: Từ tên + mô tả + ảnh, AI đề xuất tag, danh mục phù hợp và từ khóa tìm kiếm; seller xác nhận trước khi áp dụng. | E13: Nên có | F13: Trung bình | G13: LLM classify vào cây danh mục có sẵn (đưa danh sách danh mục vào prompt); vision model cho ảnh là điểm cộng. | H13: Chưa làm
... A17: AI-15 | B17: Hạ tầng AI | C17: AI Service Layer chung | D17: Tầng service AI dùng chung: quản lý API key qua biến môi trường, retry/timeout, đếm token & chi phí, log lại prompt/response, cache kết quả, fallback khi provider lỗi. | E17: Bắt buộc | F17: Trung bình | G17: Module ai_service riêng trong Django; provider-agnostic (OpenAI/Claude/Gemini); bảng AIRequestLog phục vụ debug và báo cáo đồ án. | H17: Chưa làm

Sheet Bonus
A1: TÍNH NĂNG NÂNG CAO (BONUS)
A2: Mã YC | B2: Module | C2: Chức năng | D2: Mô tả chi tiết | E2: Độ ưu tiên | F2: Độ khó | G2: Gợi ý kỹ thuật | H2: Trạng thái
A3: BON-01 | B3: Vận hành | C3: Theo dõi vận chuyển | D3: Tích hợp (giả lập hoặc API hãng vận chuyển) trạng thái vận đơn chi tiết: lấy hàng, đến kho phân loại, đang giao, giao thành công; hiển thị timeline cho khách. | E3: Tùy chọn | F3: Khó | G3: Bảng ShipmentEvent; webhook giả lập hoặc GHN/GHTK sandbox. | H3: Chưa làm
A4: BON-02 | B4: Tương tác | C4: Follow shop | D4: Khách theo dõi shop yêu thích; nhận thông báo khi shop có sản phẩm mới/khuyến mãi; trang shop hiển thị số người theo dõi. | E4: Tùy chọn | F4: Dễ | G4: Bảng ShopFollower; fan-out notification qua Celery. | H4: Chưa làm
A5: BON-03 | B5: Khuyến mãi | C5: Combo sản phẩm | D5: Seller tạo combo nhiều sản phẩm với giá ưu đãi; trang chi tiết hiển thị khối 'Mua combo tiết kiệm'. | E5: Tùy chọn | F5: Trung bình | G5: Model Bundle + BundleItem; validate tồn kho mọi item khi đặt. | H5: Chưa làm
A6: BON-04 | B6: Khuyến mãi | C6: Mua kèm giảm giá | D6: Gợi ý sản phẩm mua kèm được giảm % khi mua cùng sản phẩm chính (cross-sell). | E6: Tùy chọn | F6: Trung bình | G6: Bảng AddOnDeal; áp giá ở giỏ hàng khi đủ điều kiện. | H6: Chưa làm
A7: BON-05 | B7: Tăng trưởng | C7: Affiliate | D7: Người dùng lấy link giới thiệu sản phẩm; đơn phát sinh từ link được ghi nhận hoa hồng; trang thống kê hoa hồng. | E7: Tùy chọn | F7: Khó | G7: Mã ref trên URL + cookie; bảng AffiliateClick/Commission; chống gian lận cơ bản. | H7: Chưa làm
A8: BON-06 | B8: Loyalty | C8: Điểm thưởng | D8: Tích điểm theo giá trị đơn hoàn thành; dùng điểm trừ tiền ở checkout; lịch sử tích/tiêu điểm. | E8: Tùy chọn | F8: Trung bình | G8: Bảng PointTransaction append-only; quy tắc quy đổi cấu hình được. | H8: Chưa làm
A9: BON-07 | B9: Loyalty | C9: Ví điện tử nội bộ | D9: Ví tiền trong hệ thống: nhận hoàn tiền khi hủy/hoàn đơn, thanh toán bằng số dư ví; lịch sử giao dịch ví. | E9: Tùy chọn | F9: Khó | G9: Bảng WalletTransaction; mọi thay đổi số dư qua transaction + khóa row; không bao giờ update trực tiếp balance. | H9: Chưa làm
A10: BON-08 | B10: Realtime | C10: Thông báo realtime | D10: Đẩy thông báo tức thời (đơn mới cho seller, cập nhật đơn cho khách) qua WebSocket thay vì đợi reload. | E10: Nên có | F10: Trung bình | G10: Dùng chung hạ tầng Channels với chat; group theo user_id. | H10: Chưa làm
A11: BON-09 | B11: Bán hàng | C11: Waitlist khi hết hàng | D11: Nút 'Báo tôi khi có hàng' trên sản phẩm hết hàng; khi nhập kho, hệ thống tự gửi thông báo/email cho người chờ. | E11: Tùy chọn | F11: Dễ | G11: Bảng StockAlert; signal khi tồn > 0 thì bắn job thông báo. | H11: Chưa làm
A12: BON-10 | B12: Quản trị | C12: Báo cáo vi phạm | D12: Khách/seller báo cáo sản phẩm, review, shop vi phạm; Admin có hàng chờ xử lý tập trung. | E12: Tùy chọn | F12: Dễ | G12: Model Report dạng generic (content_type + object_id). | H12: Chưa làm
A13: BON-11 | B13: Dữ liệu | C13: Import / Export Excel | D13: Seller import sản phẩm hàng loạt từ file Excel mẫu (validate từng dòng, báo lỗi chi tiết); export danh sách sản phẩm/đơn hàng ra Excel. | E13: Nên có | F13: Trung bình | G13: openpyxl; xử lý file lớn bằng Celery; trả file lỗi kèm chú thích từng dòng. | H13: Chưa làm
... A16: BON-14 | B16: Realtime | C16: Flash Sale realtime | D16: Trong trang Flash Sale, số lượng còn lại cập nhật realtime; thanh tiến trình 'đã bán x%'. | E16: Tùy chọn | F16: Khó | G16: WebSocket broadcast khi tồn sale thay đổi; chống oversell bằng atomic decrement trong Redis/DB. | H16: Chưa làm

Sheet Phi chức năng
A1: YÊU CẦU PHI CHỨC NĂNG (NON-FUNCTIONAL)
A2: Mã YC | B2: Module | C2: Chức năng | D2: Mô tả chi tiết | E2: Độ ưu tiên | F2: Độ khó | G2: Gợi ý kỹ thuật | H2: Trạng thái
A3: NFR-01 | B3: Bảo mật | C3: Xác thực & phiên đăng nhập | D3: JWT access ngắn hạn + refresh token; refresh rotation & blacklist khi logout; mật khẩu hash (PBKDF2/argon2); không lộ token trong URL. | E3: Bắt buộc | F3: Trung bình | G3: simplejwt ROTATE_REFRESH_TOKENS; access lưu memory, refresh httpOnly cookie là điểm cộng. | H3: Chưa làm
A4: NFR-02 | B4: Bảo mật | C4: Phân quyền chặt ở API | D4: Mọi endpoint khai báo permission rõ ràng; seller chỉ thao tác dữ liệu shop mình, khách chỉ thấy đơn của mình (object-level permission); test phân quyền tối thiểu cho các API nhạy cảm. | E4: Bắt buộc | F4: Trung bình | G4: DRF permission + queryset scoping theo user; không tin ID từ client. | H4: Chưa làm
A5: NFR-03 | B5: Bảo mật | C5: Chống tấn công phổ biến | D5: Chống SQL injection (dùng ORM), XSS (sanitize rich-text), CSRF; rate limit endpoint đăng nhập/OTP; validate & giới hạn upload file (loại, dung lượng); ẩn thông tin lỗi chi tiết ở production. | E5: Bắt buộc | F5: Trung bình | G5: bleach/nh3 sanitize mô tả; django-ratelimit; kiểm tra content-type thật của file. | H5: Chưa làm
A6: NFR-04 | B6: Bảo mật | C6: Quản lý secrets | D6: Toàn bộ khóa bí mật (DB, JWT, AI API key, payment) qua biến môi trường/.env; không commit secrets vào git. | E6: Bắt buộc | F6: Dễ | G6: django-environ; .env.example trong repo; kiểm tra bằng gitleaks là điểm cộng. | H6: Chưa làm
A7: NFR-05 | B7: Hiệu năng | C7: Phân trang & tối ưu truy vấn | D7: Mọi danh sách đều phân trang; tránh N+1 query (select_related/prefetch_related); index cho các cột lọc/sắp xếp chính; API danh sách chính phản hồi < 500ms với dữ liệu mẫu ≥ 10k sản phẩm. | E7: Bắt buộc | F7: Trung bình | G7: django-debug-toolbar / nplusone khi dev; seed script sinh dữ liệu lớn để test. | H7: Chưa làm
A8: NFR-06 | B8: Hiệu năng | C8: Redis Cache | D8: Cache dữ liệu đọc nhiều: trang chủ, cây danh mục, chi tiết sản phẩm, kết quả AI; có chiến lược invalidate khi dữ liệu đổi. | E8: Nên có | F8: Trung bình | G8: django-redis; cache key theo version; TTL hợp lý từng loại. | H8: Chưa làm
A9: NFR-07 | B9: Hiệu năng | C9: Background jobs | D9: Tác vụ chậm chạy nền: gửi email, sinh nội dung AI, re-index embeddings, xuất Excel, thống kê định kỳ. | E9: Bắt buộc | F9: Trung bình | G9: Celery + Redis broker; Celery beat cho job định kỳ; retry có backoff. | H9: Chưa làm
A10: NFR-08 | B10: Kiến trúc | C10: Thiết kế API & tài liệu | D10: API RESTful đặt tên nhất quán, version /api/v1/; response format thống nhất (data/error); tài liệu tự sinh Swagger/OpenAPI đầy đủ. | E10: Bắt buộc | F10: Dễ | G10: drf-spectacular; viết mô tả serializer đầy đủ. | H10: Chưa làm
A11: NFR-09 | B11: Kiến trúc | C11: Cấu trúc code FE | D11: Vue 3 + TypeScript chuẩn: Composition API, Pinia store theo domain, tách API layer (axios instance + interceptor), component tái sử dụng, ESLint + Prettier pass. | E11: Bắt buộc | F11: Trung bình | G11: Cấu trúc thư mục features/; strict mode TypeScript; env qua import.meta.env. | H11: Chưa làm
A12: NFR-10 | B12: Kiến trúc | C12: Database design | D12: ERD đầy đủ trước khi code; chuẩn hóa hợp lý; migration quản lý bằng Django; constraint ở tầng DB (unique, check, FK); seed data mẫu. | E12: Bắt buộc | F12: Trung bình | G12: Vẽ ERD (dbdiagram.io); fixtures/management command seed. | H12: Chưa làm
A13: NFR-11 | B13: Triển khai | C13: Docker hóa toàn bộ | D13: docker-compose chạy được toàn hệ thống 1 lệnh: frontend (build Vite → Nginx), backend (gunicorn), celery worker + beat, redis; kết nối PostgreSQL external qua biến môi trường; Dockerfile multi-stage. | E13: Bắt buộc | F13: Trung bình | G13: Nginx reverse proxy: / → FE static, /api & /ws → backend; healthcheck từng service. | H13: Chưa làm
... A18: NFR-16 | B18: Vận hành | C18: Sao lưu & khôi phục dữ liệu | D18: Hướng dẫn/script backup PostgreSQL định kỳ và khôi phục; media files có chiến lược lưu trữ rõ ràng. | E18: Tùy chọn | F18: Dễ | G18: pg_dump cron; tài liệu runbook ngắn. | H18: Chưa làm

Sheet Đánh giá
A1: TIÊU CHÍ ĐÁNH GIÁ ĐỒ ÁN
A2: Nhóm tiêu chí | B2: Tiêu chí | C2: Trọng số (%) | D2: Yêu cầu liên quan
A3: Bắt buộc (40%) | B3: Authentication (đăng ký, đăng nhập, JWT, Google Login) | C3: 8 | D3: CUS-01..04, NFR-01
A4: Bắt buộc (40%) | B4: Authorization / phân quyền 3 vai trò | C4: 6 | D4: ADM-08, NFR-02
A5: Bắt buộc (40%) | B5: CRUD đầy đủ (sản phẩm, danh mục, người dùng...) | C5: 8 | D5: ADM-04..05, SEL-02..04
A6: Bắt buộc (40%) | B6: Quản lý kho (nhập/xuất, lịch sử, cảnh báo) | C6: 6 | D6: SEL-06..09
A7: Bắt buộc (40%) | B7: Giỏ hàng & đặt hàng (checkout, luồng trạng thái đơn) | C7: 8 | D7: CUS-13..17, SEL-10
A8: Bắt buộc (40%) | B8: Dashboard thống kê Admin & Seller | C8: 4 | D8: ADM-01..03, SEL-01
A9: Nâng cao (20%) | B9: Upload ảnh/video, phân trang, bộ lọc đa tiêu chí | C9: 6 | D9: SEL-03, CUS-08..09, NFR-05
A10: Nâng cao (20%) | B10: Voucher (sàn + shop) & Wishlist | C10: 5 | D10: ADM-20, SEL-12, CUS-12
A11: Nâng cao (20%) | B11: Review + trả lời review, biểu đồ thống kê | C11: 5 | D11: CUS-19, SEL-14, ADM-02
A12: Nâng cao (20%) | B12: Chat realtime, thông báo | C12: 4 | D12: SEL-16, CUS-20..21
A13: AI (25%) | B13: Smart Search + semantic search | C13: 7 | D13: AI-01..02
A14: AI (25%) | B14: Chatbot tư vấn mua hàng | C14: 6 | D14: AI-05
... A20: Bonus (15%) | B20: Unit test + Integration test, Logging | C20: 3 | D20: NFR-14..15
A21: TỔNG | C21: =SUM(C3:C20) -> 100
